jip/__init__.py
jip/cache.py
jip/commands.py
jip/dist.py
jip/embed.py
jip/index.py
jip/main.py
jip/maven.py
jip/repository.py
jip/search.py
jip/util.py
jip-0.9.16.data/data/data/pom.tpl
jip-0.9.16.data/scripts/jython-all
jip-0.9.16.dist-info/LICENSE
jip-0.9.16.dist-info/METADATA
jip-0.9.16.dist-info/WHEEL
jip-0.9.16.dist-info/entry_points.txt
jip-0.9.16.dist-info/top_level.txt
jip-0.9.16.dist-info/RECORD
