Metadata-Version: 2.1
Name: jip
Version: 0.9.16
Summary: jip installs packages, for Jython and Python
Home-page: https://github.com/sunng87/jip
Author: Sun Ning
Author-email: classicning@gmail.com
License: mit
Classifier: Development Status :: 4 - Beta
Classifier: Intended Audience :: Developers
Classifier: License :: OSI Approved :: MIT License
Classifier: Topic :: Software Development :: Build Tools
Classifier: Programming Language :: Python :: 2.6
Classifier: Programming Language :: Python :: 2.7
Classifier: Programming Language :: Python :: 3.4
Classifier: Programming Language :: Java
Classifier: Environment :: Console
Classifier: Operating System :: POSIX
License-File: LICENSE
Requires-Dist: requests
